[
null,
{"id":1,"battlerName":"Actor1_1","characterIndex":0,"characterName":"Actor1","classId":1,"equips":[1,1,0],"faceIndex":0,"faceName":"Actor1","traits":[{"code":11,"dataId":6,"value":0.5},{"code":11,"dataId":7,"value":2},{"code":34,"dataId":0,"value":1}],"initialLevel":1,"maxLevel":80,"name":"Epsilon","nickname":"","note":"the hero\nwho will the everyman be","profile":"Sla. | Prc. | Imp. | Fire | Ice | Elec | Air | Light | Dark\n --  |  --  |  --  |  --  |  -- |  St  |  Wk |   --  |  --"},
{"id":2,"battlerName":"Actor1_3","characterIndex":2,"characterName":"Actor1","classId":2,"equips":[11,2,0],"faceIndex":2,"faceName":"Actor1","traits":[{"code":11,"dataId":5,"value":2},{"code":11,"dataId":4,"value":0.5}],"initialLevel":5,"maxLevel":80,"name":"Gamma","nickname":"","note":"the magician","profile":"Sla. | Prc. | Imp. | Fire | Ice | Elec | Air | Light | Dark\n --  |  --  |  --  |  St  |  Wk |  --  |  -- |  --   |  --"},
{"id":3,"battlerName":"Actor2_1","characterIndex":0,"characterName":"Actor2","classId":3,"equips":[21,1,65],"faceIndex":0,"faceName":"Actor2","traits":[{"code":11,"dataId":4,"value":2},{"code":11,"dataId":5,"value":0.5}],"initialLevel":10,"maxLevel":80,"name":"Tau","nickname":"","note":"the lover","profile":"Sla. | Prc. | Imp. | Fire | Ice | Elec | Air | Light | Dark\n --  |  --  |  --  |  Wk  | St  |  --  |  -- |  --   |  --"},
{"id":4,"battlerName":"Actor1_4","characterIndex":3,"characterName":"Actor1","classId":4,"equips":[31,1,0],"faceIndex":3,"faceName":"Actor1","traits":[{"code":11,"dataId":9,"value":3.5},{"code":11,"dataId":7,"value":0.5},{"code":34,"dataId":0,"value":2}],"initialLevel":15,"maxLevel":80,"name":"Alfa","nickname":"","note":"the jester","profile":"Sla. | Prc. | Imp. | Fire | Ice | Elec | Air | Light | Dark\n --  |  --  |  --  |  --  |  -- |  --  | St  |  --   |  Wk"},
{"id":5,"battlerName":"Actor3_5","characterIndex":4,"characterName":"Actor3","classId":6,"equips":[7,0,65],"faceIndex":4,"faceName":"Actor3","traits":[{"code":11,"dataId":8,"value":3.5},{"code":11,"dataId":4,"value":0.5},{"code":34,"dataId":0,"value":1}],"initialLevel":25,"maxLevel":80,"name":"Sigma","nickname":"","note":"the outlaw","profile":"Sla. | Prc. | Imp. | Fire | Ice | Elec | Air | Light | Dark\n --  |  --  |  --  |  St  |  -- |  --  |  -- |  Wk   |  --"},
{"id":6,"battlerName":"Actor1_5","characterIndex":4,"characterName":"Actor1","classId":7,"equips":[7,0,0],"faceIndex":4,"faceName":"Actor1","traits":[{"code":11,"dataId":9,"value":3.5},{"code":11,"dataId":8,"value":0.5}],"initialLevel":30,"maxLevel":80,"name":"Lambda","nickname":"","note":"the caregiver","profile":"Sla. | Prc. | Imp. | Fire | Ice | Elec | Air | Light | Dark\n --  |  --  |  --  |  --  |  -- |  --  |  -- |  St   |  Wk"},
{"id":7,"battlerName":"Actor1_8","characterIndex":7,"characterName":"Actor1","classId":8,"equips":[7,0,0],"faceIndex":7,"faceName":"Actor1","traits":[],"initialLevel":35,"maxLevel":80,"name":"Iota","nickname":"","note":"the sage","profile":"Sla. | Prc. | Imp. | Fire | Ice | Elec | Air | Light | Dark\n --  |  --  |  --  |  --  |  -- |  Wk  |  St |  --   |  --"},
{"id":8,"battlerName":"Actor2_8","characterIndex":7,"characterName":"Actor2","classId":9,"equips":[0,0,0,0,0],"faceIndex":7,"faceName":"Actor2","traits":[],"initialLevel":40,"maxLevel":80,"name":"Kappa","nickname":"","note":"the innocent","profile":"Sla. | Prc. | Imp. | Fire | Ice | Elec | Air | Light | Dark\n St  |  --  |  --  |  --  |  -- |  --  |  -- |  Wk   |  --"},
{"id":9,"battlerName":"Actor2_5","characterIndex":4,"characterName":"Actor2","classId":1,"equips":[0,0,0,0,0],"faceIndex":4,"faceName":"Actor2","traits":[{"code":11,"dataId":9,"value":3.5},{"code":11,"dataId":6,"value":0.5},{"code":62,"dataId":0,"value":1}],"initialLevel":1,"maxLevel":80,"name":"Omicron","nickname":"","note":"the ruler\nany fight he's in should change his\nnickname right before battle start to\nreflect the rank of the ruler s-link","profile":"Sla. | Prc. | Imp. | Fire | Ice | Elec | Air | Light | Dark\n ??  |  ??  |  ??  |  ??  |  ?? |  ??  |  ?? |  ??   |  ??"}
]